[{"user_id":"1","name":"Else Bradtke","email":"oral.legros@example.net","password":"cef0abba639e7f9fa9ca6545322524ec344c19a7","username":"gerald26"},{"user_id":"2","name":"Aditya Dare","email":"ihartmann@example.net","password":"aba91b7c220d5c31a5b41c55f0e1abada90c7d99","username":"jaqueline70"},{"user_id":"3","name":"Delilah Glover","email":"lulu28@example.org","password":"18347bd42e09f1a870e9307938078df55bd0b435","username":"gregoria.cassin"},{"user_id":"4","name":"Oma Runte","email":"ykilback@example.com","password":"8a2da50e8c8fc92011c878de8ef0fd73358c51f5","username":"mfranecki"},{"user_id":"5","name":"Loy Windler","email":"river61@example.net","password":"4aaa318d3cd32b324a7c4b23967f48ccaecc3467","username":"samantha47"},{"user_id":"6","name":"Ms. Mable Becker DDS","email":"altenwerth.dennis@example.com","password":"8704d850dc6bd3fcd3cb030ed77fb7267f58e09a","username":"mclaughlin.clarabelle"},{"user_id":"7","name":"Miss Lue Pagac III","email":"amelia.wiegand@example.org","password":"3dd46e7bbf45f876da88f5a43e77bc2c5bf16911","username":"maritza46"},{"user_id":"8","name":"Ms. Antoinette Rau Sr.","email":"jacquelyn03@example.org","password":"0ba2268dadfca2e1ba20da4190ba8104dd8ddc22","username":"judy.hills"},{"user_id":"9","name":"Jayne Purdy MD","email":"mozelle05@example.org","password":"a0efb861f1749c7f371ad69e80f870ec1cb097cb","username":"kovacek.eva"},{"user_id":"10","name":"Mrs. Ona Deckow MD","email":"hansen.afton@example.net","password":"2d6914753d6db38f64cbf94ce1d43ef2d2afbc9c","username":"fhettinger"},{"user_id":"11","name":"Heather Strosin","email":"jamarcus65@example.com","password":"7f1ce3f40b3109af30c5355bec7a7b7d59e63806","username":"crist.orville"},{"user_id":"12","name":"Victor Gaylord","email":"jeanette88@example.org","password":"c9ae775658eaed03f79ed1b4000dfb81a8274d8f","username":"lionel08"},{"user_id":"13","name":"Marcelo Mertz","email":"bmorar@example.org","password":"c09111a584f632980569f530ccc1fd46ea212a88","username":"krolfson"},{"user_id":"14","name":"Saul Legros","email":"bradtke.lelah@example.net","password":"f640718c4f06745b78567cf8cead37c5777ccaca","username":"maya.ziemann"},{"user_id":"15","name":"Elinore Rodriguez","email":"dtillman@example.org","password":"907c4a23ed897d827f4754016376b04f5487b57c","username":"klemke"},{"user_id":"16","name":"Kole Schmitt","email":"kuhlman.christophe@example.com","password":"2c22de1d57dbd97c29d30456b29fd420a0014c2b","username":"casandra.predovic"},{"user_id":"17","name":"Carley Wisozk","email":"tanner.kling@example.net","password":"74cbccfd62f868c9b3d4a00b73b119d6aefbf099","username":"neal.hoeger"},{"user_id":"18","name":"Stanton Ward","email":"lillian.beatty@example.com","password":"83115f878c5cca0de50ccba1e0439961d8687da8","username":"mary14"},{"user_id":"19","name":"Daisy Bogan IV","email":"ojast@example.net","password":"7fbce46314cd3b8c7e611ca83a581343e8c2c9b6","username":"czemlak"},{"user_id":"20","name":"Eleonore Sanford","email":"gaylord.oberbrunner@example.org","password":"b97ccc5871bc4e84433cddbe415ce16c1b1c25c8","username":"qkonopelski"},{"user_id":"21","name":"Madeline Harvey","email":"zrau@example.net","password":"5365e40d5dd9bcc4b34d9703dde6da798ef7d530","username":"monty.crist"},{"user_id":"22","name":"Jeffry D'Amore","email":"christophe.kihn@example.com","password":"c95b616d02d0fafaef1c1c7a177cc10fd1cfdf50","username":"pfannerstill.justen"},{"user_id":"23","name":"Ms. Guadalupe Raynor","email":"davis.lambert@example.net","password":"b493fd9746a07c57b85f392f7c722c31c69efa42","username":"ddenesik"},{"user_id":"24","name":"Jaquelin Harvey","email":"ahmad91@example.com","password":"f4810aa54d890b8164fe6b87ca20d25677820dcb","username":"schmitt.saige"},{"user_id":"25","name":"Buster Rippin","email":"tbartoletti@example.net","password":"cbba24a7e912245aa0819c3cbde94ad1e44071a7","username":"block.alene"},{"user_id":"26","name":"Prof. Jessie Senger","email":"plang@example.net","password":"94d4bd4279a3309a337f33440f0182b05047880c","username":"irving06"},{"user_id":"27","name":"Dr. Providenci Becker","email":"gutmann.kelly@example.com","password":"a99c57e107edb8026ffa19c1ea659483deb8b2a9","username":"adelia15"},{"user_id":"28","name":"Summer Aufderhar","email":"wkoepp@example.org","password":"0978de66b11ffcbdbb1df6486e296d9f7c093d19","username":"gia72"},{"user_id":"29","name":"Mr. Chesley Deckow IV","email":"qzemlak@example.org","password":"ba8ec06c49bd16c2d4532d2bc6016502fee1607d","username":"zmiller"},{"user_id":"30","name":"Graciela Johnston","email":"qblick@example.org","password":"04a06b969f76bd819e3acd9376a144a3240b3639","username":"korbin85"},{"user_id":"31","name":"Silas Frami","email":"hester.ankunding@example.org","password":"2f38ebe5e66012d09b950e95548c27f934aa24cc","username":"philip71"},{"user_id":"32","name":"Mrs. Aurelia Stiedemann PhD","email":"gilbert.dickinson@example.com","password":"6eefa67f8d87059de07bbe165a64716db6a728ec","username":"yvonne.pfeffer"},{"user_id":"33","name":"Manuela Turcotte","email":"orodriguez@example.org","password":"1da40832c07a2b60b967658b056028ce5fff6c2b","username":"watsica.elna"},{"user_id":"34","name":"Kristofer Mayer MD","email":"rogers.breitenberg@example.com","password":"26c27308b2ea016bfc5615b4ede3d74aadcaf38e","username":"murphy.arno"},{"user_id":"35","name":"Jayde McCullough","email":"blemke@example.net","password":"40e45f1aded3bf4fda24a9e146a304e8c00a1b02","username":"clarissa56"},{"user_id":"36","name":"Bell Bogisich","email":"mhodkiewicz@example.org","password":"a0be2977b8d8164c0cc2e47941ebd8b07ef3dfb2","username":"lavonne.hahn"},{"user_id":"37","name":"Will Sawayn","email":"bergnaum.polly@example.net","password":"b62b8b3102bec0e8096db790f6962e0c0071652e","username":"hkreiger"},{"user_id":"38","name":"Lizzie Pfannerstill PhD","email":"destini.predovic@example.net","password":"cba61f00cd5772ca4949a65daba598f4f5d94060","username":"alan.blanda"},{"user_id":"39","name":"Shanel Spencer MD","email":"saul.fadel@example.com","password":"67e2138fe96f10fc19f3996ee62855d6dc7596ff","username":"miguel28"},{"user_id":"40","name":"Prof. Eldon Emard III","email":"mollie42@example.net","password":"6f841f6df1b68602c18e01d35fa53fe760c9207c","username":"avis75"},{"user_id":"41","name":"Norbert Oberbrunner","email":"dvon@example.net","password":"b56661482951e35293e6b7529fe2097e8cfd1065","username":"lonnie59"},{"user_id":"42","name":"Jarod Shanahan","email":"aniyah.cummerata@example.net","password":"faedaa67247aa26a1f64dd2c5f5e4f5ddead25ce","username":"labadie.gabriel"},{"user_id":"43","name":"Darby Dickinson MD","email":"mandy99@example.net","password":"551e2cf226a361a59c37d1d1bc9a7c8d9e33b913","username":"katrine42"},{"user_id":"44","name":"Elise Wisoky","email":"anahi.ryan@example.net","password":"b7893b35a550fc80568c5389dff72071d923a56f","username":"hanna00"},{"user_id":"45","name":"Isaias Cummings","email":"iwindler@example.com","password":"db4c84057eef742bd5cf95f5e3545a9d9970349a","username":"juwan46"},{"user_id":"46","name":"Dr. Coty McDermott I","email":"zelma.kessler@example.net","password":"0832bcda1c5c41b29b43484ea4c972bfdd12b1d3","username":"arthur.mueller"},{"user_id":"47","name":"Serena Schowalter","email":"ifadel@example.net","password":"7a771536ea7f7117e2acff7acd4826bbd3ffa420","username":"roob.raina"},{"user_id":"48","name":"Pascale Botsford","email":"christiansen.damon@example.net","password":"a2088d2421bf41e9325ca5434d243c0a39ed3cf8","username":"beatrice01"},{"user_id":"49","name":"Trent Bergnaum","email":"kvon@example.org","password":"f4b9b73ad8c4574e1fed40408856a2d71bf50a3f","username":"janis.lynch"},{"user_id":"50","name":"Elenor Kihn","email":"justice.gleichner@example.com","password":"d401acb9b51078339af756d4bedb09a6b336dd24","username":"conn.corbin"}]
